format_textview/__init__.py
format_textview/format_textview.glade~
format_textview/gtk/__init__.py
format_textview/gtk/format_textview.glade
format_textview/gtk/format_textview.py
format_textview/tests/__init__.py
format_textview/tests/manual_testing.py
gtk_formatted_textview-0.2.0.dist-info/WHEEL
gtk_formatted_textview-0.2.0.dist-info/METADATA
gtk_formatted_textview-0.2.0.dist-info/RECORD
